gsf/__init__.py
gsf/control/__init__.py
gsf/control/controls/__init__.py
gsf/control/controls/discrete_event_control.py
gsf/control/controls/thread_control.py
gsf/control/core/__init__.py
gsf/control/core/base_control.py
gsf/control/core/simulation_stats.py
gsf/control/core/simulation_strategy.py
gsf/core/__init__.py
gsf/core/config.py
gsf/core/debug/__init__.py
gsf/core/debug/domain/__init__.py
gsf/core/debug/domain/debug.py
gsf/core/debug/domain/summary_table.py
gsf/core/debug/infrastructure/__init__.py
gsf/core/debug/infrastructure/providers.py
gsf/core/debug/infrastructure/table.py
gsf/core/entity/__init__.py
gsf/core/entity/core/__init__.py
gsf/core/entity/core/entity.py
gsf/core/entity/core/entity_emitter.py
gsf/core/entity/core/entity_manager.py
gsf/core/entity/core/entity_property.py
gsf/core/entity/core/property_type.py
gsf/core/entity/properties/__init__.py
gsf/core/entity/properties/boolean_property.py
gsf/core/entity/properties/expression_property.py
gsf/core/entity/properties/number_property.py
gsf/core/entity/properties/property.py
gsf/core/entity/properties/string_property.py
gsf/core/events/__init__.py
gsf/core/events/domain_events.py
gsf/core/events/event_bus.py
gsf/core/expressions/__init__.py
gsf/core/expressions/expression.py
gsf/core/expressions/user_expression.py
gsf/core/mathematics/__init__.py
gsf/core/mathematics/distributions/__init__.py
gsf/core/mathematics/distributions/exponential_distribution.py
gsf/core/mathematics/distributions/poisson_distribution.py
gsf/core/mathematics/distributions/random_distribution.py
gsf/core/mathematics/distributions/triangular_distribution.py
gsf/core/mathematics/values/__init__.py
gsf/core/mathematics/values/value.py
gsf/core/time/__init__.py
gsf/core/time/simulation_time.py
gsf/core/types/__init__.py
gsf/core/types/dynamic_system_input.py
gsf/core/types/model_input.py
gsf/core/types/time.py
gsf/dynamic_system/__init__.py
gsf/dynamic_system/core/__init__.py
gsf/dynamic_system/core/base_dynamic_sytem.py
general_simulation_framework-1.0.1.dist-info/LICENSE
general_simulation_framework-1.0.1.dist-info/METADATA
general_simulation_framework-1.0.1.dist-info/WHEEL
general_simulation_framework-1.0.1.dist-info/top_level.txt
general_simulation_framework-1.0.1.dist-info/RECORD
