Metadata-Version: 2.1
Name: general-simulation-framework
Version: 1.0.1
Summary: General Simulation Framework
Home-page: https://github.com/RolandoAndrade/general-simulation-framework
Author: Rolando Andrade
Author-email: rolandoandradefernandez@gmail.com
License: UNKNOWN
Project-URL: Bug Tracker, https://github.com/RolandoAndrade/general-simulation-framework/issues
Platform: UNKNOWN
Classifier: Programming Language :: Python :: 3
Classifier: License :: OSI Approved :: MIT License
Classifier: Operating System :: OS Independent
Requires-Python: >=3.6
License-File: LICENSE
Requires-Dist: numpy (==1.21.1)
Requires-Dist: loguru (==0.5.3)
Requires-Dist: prettytable (==2.1.0)
Requires-Dist: event-bus (==1.0.2)
Requires-Dist: graphviz (==0.17)
